{
 "generatedAt": "2026-07-22T11:28:27+0700",
 "count": 5,
 "source": "Bao Moi - bai da luu (loc dung 4 chu de cua web + chi bai dang trong 24h, tu dong qua GitHub Action)",
 "items": [
  {
   "date": "2026-07-21",
   "category": "Công nghệ quân sự",
   "title": "Mỹ siết chặt chuỗi cung ứng quốc phòng với Trung Quốc",
   "summary": "",
   "sourceName": "Chuyên trang An Ninh Thủ Đô - Báo Công an nhân dân",
   "sourceUrl": "https://baomoi.com/my-siet-chat-chuoi-cung-ung-quoc-phong-voi-trung-quoc-c55663663.epi",
   "region": "Đông Á"
  },
  {
   "date": "2026-07-21",
   "category": "Chính trị",
   "title": "Bầu cử giữa kỳ Mỹ năm 2026 và 'những khoảng trống tín nhiệm'",
   "summary": "",
   "sourceName": "Báo Thế Giới & Việt Nam",
   "sourceUrl": "https://baomoi.com/bau-cu-giua-ky-my-nam-2026-va-nhung-khoang-trong-tin-nhiem-c55665288.epi",
   "region": ""
  },
  {
   "date": "2026-07-21",
   "category": "Kinh tế",
   "title": "Mỹ chuẩn bị áp mức thuế mới với 60 đối tác thương mại",
   "summary": "",
   "sourceName": "Báo Tin Tức TTXVN",
   "sourceUrl": "https://baomoi.com/my-chuan-bi-ap-muc-thue-moi-voi-60-doi-tac-thuong-mai-c55665400.epi",
   "region": ""
  },
  {
   "date": "2026-07-22",
   "category": "Công nghệ quân sự",
   "title": "Patriot có tên lửa đánh chặn giá rẻ",
   "summary": "",
   "sourceName": "Tạp chí Tri thức",
   "sourceUrl": "https://baomoi.com/patriot-co-ten-lua-danh-chan-gia-re-c55665752.epi",
   "region": ""
  },
  {
   "date": "2026-07-22",
   "category": "Ngoại giao",
   "title": "Trung Quốc sẵn sàng tăng cường hợp tác với ASEAN",
   "summary": "",
   "sourceName": "Báo VietnamPlus",
   "sourceUrl": "https://baomoi.com/trung-quoc-san-sang-tang-cuong-hop-tac-voi-asean-c55666063.epi",
   "region": "Đông Á"
  }
 ]
}