{
 "generatedAt": "2026-07-19T16:15:16+0700",
 "count": 44,
 "source": "Bao Moi - bai da luu (tu dong qua GitHub Action)",
 "items": [
  {
   "id": 55598065,
   "title": "Mỹ rút tiêm kích tàng hình 'F-22 Raptor' khỏi Israel sau chiến dịch tập kích Iran",
   "url": "https://baomoi.com/my-rut-tiem-kich-tang-hinh-f-22-raptor-khoi-israel-sau-chien-dich-tap-kich-iran-c55598065.epi",
   "source": "Chuyên trang An Ninh Thủ Đô - Báo Công an nhân dân",
   "date": "2026-07-12",
   "ts": 1783826310,
   "thumb": "https://photo-baomoi.bmcdn.me/w700_r16x9/2026_07_12_106_55598065/0d2f6a393872d12c8863.jpg",
   "isVideo": true,
   "category": "Quân sự & Quốc phòng"
  },
  {
   "id": 55598128,
   "title": "Mỹ nới kiểm soát xuất khẩu chip tiên tiến và UAV cho UAE",
   "url": "https://baomoi.com/my-noi-kiem-soat-xuat-khau-chip-tien-tien-va-uav-cho-uae-c55598128.epi",
   "source": "Báo Tin Tức TTXVN",
   "date": "2026-07-12",
   "ts": 1783826940,
   "thumb": "https://photo-baomoi.bmcdn.me/w700_r16x9/2026_07_12_294_55598128/ffac41bb13f0faaea3e1.jpg",
   "isVideo": false,
   "category": "Kinh tế & Năng lượng"
  },
  {
   "id": 55597699,
   "title": "NATO thể hiện một thiện chí đối thoại với Nga",
   "url": "https://baomoi.com/nato-the-hien-mot-thien-chi-doi-thoai-voi-nga-c55597699.epi",
   "source": "Báo Thế Giới & Việt Nam",
   "date": "2026-07-12",
   "ts": 1783831500,
   "thumb": "https://photo-baomoi.bmcdn.me/w700_r16x9/2026_07_12_194_55597699/7482509e02d5eb8bb2c4.jpg",
   "isVideo": false,
   "category": "Quân sự & Quốc phòng"
  },
  {
   "id": 55599635,
   "title": "Syria kỳ vọng hồi sinh kinh tế sau thời 'quốc gia bảo trợ khủng bố'",
   "url": "https://baomoi.com/syria-ky-vong-hoi-sinh-kinh-te-sau-thoi-quoc-gia-bao-tro-khung-bo-c55599635.epi",
   "source": "Báo Hà Nội Mới",
   "date": "2026-07-12",
   "ts": 1783843020,
   "thumb": "https://photo-baomoi.bmcdn.me/w700_r16x9/2026_07_12_8_55599635/c0ac3e4e6d05845bdd14.jpg",
   "isVideo": false,
   "category": "Kinh tế & Năng lượng"
  },
  {
   "id": 55599768,
   "title": "Ông Trump đạt thỏa thuận khánh thành cây cầu 4,7 tỷ USD nối Mỹ với Canada",
   "url": "https://baomoi.com/ong-trump-dat-thoa-thuan-khanh-thanh-cay-cau-4-7-ty-usd-noi-my-voi-canada-c55599768.epi",
   "source": "Báo VietnamNet",
   "date": "2026-07-12",
   "ts": 1783846680,
   "thumb": "https://photo-baomoi.bmcdn.me/w700_r16x9/2026_07_12_23_55599768/a64342af11e4f8baa1f5.jpg",
   "isVideo": false,
   "category": "Ngoại giao & Thế giới"
  },
  {
   "id": 55601112,
   "title": "Nga ra quyết định mới với dầu diesel, thị trường toàn cầu phản ứng",
   "url": "https://baomoi.com/nga-ra-quyet-dinh-moi-voi-dau-diesel-thi-truong-toan-cau-phan-ung-c55601112.epi",
   "source": "Báo VietnamNet",
   "date": "2026-07-12",
   "ts": 1783867320,
   "thumb": "https://photo-baomoi.bmcdn.me/w700_r16x9/2026_07_12_23_55601112/839e226271299877c138.jpg",
   "isVideo": false,
   "category": "Kinh tế & Năng lượng"
  },
  {
   "id": 55602423,
   "title": "Cạnh tranh kiểm soát eo biển Hormuz định hình tương lai dòng chảy dầu mỏ",
   "url": "https://baomoi.com/canh-tranh-kiem-soat-eo-bien-hormuz-dinh-hinh-tuong-lai-dong-chay-dau-mo-c55602423.epi",
   "source": "Báo Tin Tức TTXVN",
   "date": "2026-07-13",
   "ts": 1783904520,
   "thumb": "https://photo-baomoi.bmcdn.me/w700_r16x9/2026_07_13_294_55602423/9533eff0bcbb55e50caa.jpg",
   "isVideo": false,
   "category": "Kinh tế & Năng lượng"
  },
  {
   "id": 55602571,
   "title": "Cơ quan Hàng không Vũ trụ Nhật Bản thử nghiệm tên lửa tái sử dụng",
   "url": "https://baomoi.com/co-quan-hang-khong-vu-tru-nhat-ban-thu-nghiem-ten-lua-tai-su-dung-c55602571.epi",
   "source": "Chuyên trang An Ninh Thủ Đô - Báo Công an nhân dân",
   "date": "2026-07-13",
   "ts": 1783909184,
   "thumb": "https://photo-baomoi.bmcdn.me/w700_r16x9/2026_07_13_106_55602571/c56b3ea66ded84b3ddfc.jpg",
   "isVideo": false,
   "category": "Quân sự & Quốc phòng"
  },
  {
   "id": 55602667,
   "title": "Mỹ cảnh báo siết thương mại với các nước 'phớt lờ' an ninh Mỹ",
   "url": "https://baomoi.com/my-canh-bao-siet-thuong-mai-voi-cac-nuoc-phot-lo-an-ninh-my-c55602667.epi",
   "source": "Bnews",
   "date": "2026-07-13",
   "ts": 1783909620,
   "thumb": "https://photo-baomoi.bmcdn.me/w700_r16x9/2026_07_13_324_55602667/4fd4bf1aec51050f5c40.jpg",
   "isVideo": false,
   "category": "Kinh tế & Năng lượng"
  },
  {
   "id": 55602018,
   "title": "Thủ tướng Ukraine bất ngờ tuyên bố từ chức, Tổng thống Zelensky nói gì?",
   "url": "https://baomoi.com/thu-tuong-ukraine-bat-ngo-tuyen-bo-tu-chuc-tong-thong-zelensky-noi-gi-c55602018.epi",
   "source": "Báo Thế Giới & Việt Nam",
   "date": "2026-07-13",
   "ts": 1783903380,
   "thumb": "https://photo-baomoi.bmcdn.me/w700_r16x9/2026_07_13_194_55602018/cae35c240f6fe631bf7e.jpg",
   "isVideo": false,
   "category": "Ngoại giao & Thế giới"
  },
  {
   "id": 53219580,
   "title": "Cụ bà Hà Tĩnh 'đi' theo chồng, đám tang đôi khiến làng quê nghẹn ngào",
   "url": "https://baomoi.com/cu-ba-ha-tinh-di-theo-chong-dam-tang-doi-khien-lang-que-nghen-ngao-c53219580.epi",
   "source": "Báo VietnamNet",
   "date": "2025-09-12",
   "ts": 1757635200,
   "thumb": "https://photo-baomoi.bmcdn.me/w700_r16x9/2025_09_12_23_53219580/b226d787ccce25907cdf.jpg",
   "isVideo": false,
   "category": "Khác"
  },
  {
   "id": 52885784,
   "title": "Yamal lập cú đúp mừng áo số 10, Barca thắng to",
   "url": "https://baomoi.com/yamal-lap-cu-dup-mung-ao-so-10-barca-thang-to-c52885784.epi",
   "source": "Báo VietnamNet",
   "date": "2025-07-31",
   "ts": 1753972320,
   "thumb": "https://photo-baomoi.bmcdn.me/w700_r16x9/2025_07_31_23_52885784/1ec916a1d6ef3fb166fe.jpg",
   "isVideo": false,
   "category": "Thể thao"
  },
  {
   "id": 52819004,
   "title": "Trung Quốc phản ứng khi Nga đề xuất thành lập khối địa chính trị mới với Ấn Độ",
   "url": "https://baomoi.com/trung-quoc-phan-ung-khi-nga-de-xuat-thanh-lap-khoi-dia-chinh-tri-moi-voi-an-do-c52819004.epi",
   "source": "Báo Tin Tức TTXVN",
   "date": "2025-07-23",
   "ts": 1753267740,
   "thumb": "https://photo-baomoi.bmcdn.me/w700_r16x9/2025_07_23_294_52819004/8298d1bd1ff3f6adafe2.jpg",
   "isVideo": false,
   "category": "Ngoại giao & Thế giới"
  },
  {
   "id": 52632889,
   "title": "Doanh nghiệp đứng trước cơ hội lớn và bài toán sàng lọc khắc nghiệt",
   "url": "https://baomoi.com/doanh-nghiep-dung-truoc-co-hoi-lon-va-bai-toan-sang-loc-khac-nghiet-c52632889.epi",
   "source": "Tạp chí Doanh Nghiệp Việt Nam",
   "date": "2025-06-30",
   "ts": 1751246880,
   "thumb": "https://photo-baomoi.bmcdn.me/w700_r16x9/2025_06_30_304_52632889/a41e0efbfeb517eb4ea4.jpg",
   "isVideo": false,
   "category": "Kinh tế & Năng lượng"
  },
  {
   "id": 52597860,
   "title": "Phép thử với chiến lược năng lượng của châu Á",
   "url": "https://baomoi.com/phep-thu-voi-chien-luoc-nang-luong-cua-chau-a-c52597860.epi",
   "source": "Báo Hà Nội Mới",
   "date": "2025-06-26",
   "ts": 1750900080,
   "thumb": "https://photo-baomoi.bmcdn.me/w700_r16x9/2025_06_26_8_52597860/4b44e9671029f977a038.jpg",
   "isVideo": false,
   "category": "Kinh tế & Năng lượng"
  },
  {
   "id": 52597456,
   "title": "Mỹ ' gieo gió, gặt bão' ở Iran",
   "url": "https://baomoi.com/my-gieo-gio-gat-bao-o-iran-c52597456.epi",
   "source": "Báo Tiền Phong",
   "date": "2025-06-26",
   "ts": 1750896900,
   "thumb": "https://photo-baomoi.bmcdn.me/w700_r16x9/2025_06_26_20_52597456/7fa00a26d7683e366779.jpg",
   "isVideo": false,
   "category": "Ngoại giao & Thế giới"
  },
  {
   "id": 52570293,
   "title": "Tại sao hoạt động xuất khẩu dầu mỏ của Iran không bị ảnh hưởng bởi chiến tranh?",
   "url": "https://baomoi.com/tai-sao-hoat-dong-xuat-khau-dau-mo-cua-iran-khong-bi-anh-huong-boi-chien-tranh-c52570293.epi",
   "source": "Tạp chí Petrotimes",
   "date": "2025-06-23",
   "ts": 1750647900,
   "thumb": "https://photo-baomoi.bmcdn.me/w700_r16x9/2025_06_23_232_52570293/4374123aef74062a5f65.jpg",
   "isVideo": false,
   "category": "Kinh tế & Năng lượng"
  },
  {
   "id": 52572715,
   "title": "Kinh tế Mỹ đối mặt nguy cơ lạm phát trở lại sau 'đòn' không kích Iran",
   "url": "https://baomoi.com/kinh-te-my-doi-mat-nguy-co-lam-phat-tro-lai-sau-don-khong-kich-iran-c52572715.epi",
   "source": "Báo VietnamPlus",
   "date": "2025-06-23",
   "ts": 1750664340,
   "thumb": "https://photo-baomoi.bmcdn.me/w700_r16x9/2025_06_23_293_52572715/874a37abc9e520bb79f4.jpg",
   "isVideo": false,
   "category": "Kinh tế & Năng lượng"
  },
  {
   "id": 52574019,
   "title": "EU cảnh báo 'đụng độ kinh tế thế kỷ' với Trung Quốc",
   "url": "https://baomoi.com/eu-canh-bao-dung-do-kinh-te-the-ky-voi-trung-quoc-c52574019.epi",
   "source": "Báo Tin Tức TTXVN",
   "date": "2025-06-23",
   "ts": 1750671840,
   "thumb": "https://photo-baomoi.bmcdn.me/w700_r16x9/2025_06_23_294_52574019/d1a0d0692e27c7799e36.jpg",
   "isVideo": false,
   "category": "Kinh tế & Năng lượng"
  },
  {
   "id": 52445568,
   "title": "Bạn thích phong cách trò truyện sở hữu hay hiện hữu?",
   "url": "https://baomoi.com/ban-thich-phong-cach-tro-truyen-so-huu-hay-hien-huu-c52445568.epi",
   "source": "Tạp chí Tri thức",
   "date": "2025-06-08",
   "ts": 1749344423,
   "thumb": "https://photo-baomoi.bmcdn.me/w700_r16x9/2025_06_08_119_52445568/9085e521756f9c31c57e.jpg",
   "isVideo": false,
   "category": "Tâm lý & Kỹ năng sống"
  },
  {
   "id": 52391017,
   "title": "10 sao nữ có vóc dáng đáng khao khát nhất Hàn Quốc",
   "url": "https://baomoi.com/10-sao-nu-co-voc-dang-dang-khao-khat-nhat-han-quoc-c52391017.epi",
   "source": "Tạp chí Tri thức",
   "date": "2025-06-02",
   "ts": 1748818950,
   "thumb": "https://photo-baomoi.bmcdn.me/w700_r16x9/2025_06_02_119_52391017/91dd0e5b96157f4b2604.jpg",
   "isVideo": false,
   "category": "Giải trí"
  },
  {
   "id": 52327899,
   "title": "Hội nghị Cấp cao ASEAN 2025 dưới góc nhìn của Giáo sư Carl Thayer",
   "url": "https://baomoi.com/hoi-nghi-cap-cao-asean-2025-duoi-goc-nhin-cua-giao-su-carl-thayer-c52327899.epi",
   "source": "Báo Tin Tức TTXVN",
   "date": "2025-05-25",
   "ts": 1748170560,
   "thumb": "https://photo-baomoi.bmcdn.me/w700_r16x9/2025_05_25_294_52327899/57454eece9a200fc59b3.jpg",
   "isVideo": false,
   "category": "Ngoại giao & Thế giới"
  },
  {
   "id": 52323769,
   "title": "8 dấu hiệu cảnh báo bạn đang trở thành người độc hại",
   "url": "https://baomoi.com/8-dau-hieu-canh-bao-ban-dang-tro-thanh-nguoi-doc-hai-c52323769.epi",
   "source": "Tạp chí Tri thức",
   "date": "2025-05-25",
   "ts": 1748131218,
   "thumb": "https://photo-baomoi.bmcdn.me/w700_r16x9/2025_05_25_119_52323769/d993c2f964b78de9d4a6.jpg",
   "isVideo": false,
   "category": "Tâm lý & Kỹ năng sống"
  },
  {
   "id": 52195114,
   "title": "Bình luận: Hồi sau sẽ rõ",
   "url": "https://baomoi.com/binh-luan-hoi-sau-se-ro-c52195114.epi",
   "source": "Báo Quân Đội Nhân Dân",
   "date": "2025-05-10",
   "ts": 1746840420,
   "thumb": "https://photo-baomoi.bmcdn.me/w700_r16x9/2025_05_10_16_52195114/4de9b0170459ed07b448.jpg",
   "isVideo": false,
   "category": "Khác"
  },
  {
   "id": 51956453,
   "title": "Bùi Thạc Chuyên: 'Tôi đau đớn khi buộc phải cắt cảnh của Thái Hòa'",
   "url": "https://baomoi.com/bui-thac-chuyen-toi-dau-don-khi-buoc-phai-cat-canh-cua-thai-hoa-c51956453.epi",
   "source": "Tạp chí Tri thức",
   "date": "2025-04-12",
   "ts": 1744419740,
   "thumb": "https://photo-baomoi.bmcdn.me/w700_r16x9/2025_04_12_119_51956453/c83a42072549cc179558.jpg",
   "isVideo": false,
   "category": "Giải trí"
  },
  {
   "id": 51946249,
   "title": "3 thói quen đẩy nhanh quá trình thoái hóa não, rút ngắn tuổi thọ",
   "url": "https://baomoi.com/3-thoi-quen-day-nhanh-qua-trinh-thoai-hoa-nao-rut-ngan-tuoi-tho-c51946249.epi",
   "source": "Báo Giáo Dục & Thời Đại",
   "date": "2025-04-11",
   "ts": 1744330020,
   "thumb": "https://photo-baomoi.bmcdn.me/w700_r16x9/2025_04_11_181_51946249/5debe712815c6802314d.jpg",
   "isVideo": false,
   "category": "Sức khỏe & Dinh dưỡng"
  },
  {
   "id": 51944953,
   "title": "'Tâm lý con bạc' khi đổ vỡ trong chuyện tình cảm",
   "url": "https://baomoi.com/tam-ly-con-bac-khi-do-vo-trong-chuyen-tinh-cam-c51944953.epi",
   "source": "Tạp chí Tri thức",
   "date": "2025-04-10",
   "ts": 1744297642,
   "thumb": "https://photo-baomoi.bmcdn.me/w700_r16x9/2025_04_10_119_51944953/03b2e6f283bc6ae233ad.jpg",
   "isVideo": false,
   "category": "Tâm lý & Kỹ năng sống"
  },
  {
   "id": 51897264,
   "title": "Lý giải nhiều gia đình vẫn 'con yêu, con ghét'",
   "url": "https://baomoi.com/ly-giai-nhieu-gia-dinh-van-con-yeu-con-ghet-c51897264.epi",
   "source": "Báo Giáo Dục & Thời Đại",
   "date": "2025-04-05",
   "ts": 1743808860,
   "thumb": "https://photo-baomoi.bmcdn.me/w700_r16x9/2025_04_05_181_51897264/49548741eb0f02515b1e.jpg",
   "isVideo": false,
   "category": "Gia đình & Nuôi dạy con"
  },
  {
   "id": 51843421,
   "title": "8 dấu hiệu của cha mẹ độc đoán",
   "url": "https://baomoi.com/8-dau-hieu-cua-cha-me-doc-doan-c51843421.epi",
   "source": "Tạp chí Tri thức",
   "date": "2025-03-30",
   "ts": 1743292813,
   "thumb": "https://photo-baomoi.bmcdn.me/w700_r16x9/2025_03_30_119_51843421/bba77aa701e9e8b7b1f8.jpg",
   "isVideo": false,
   "category": "Tâm lý & Kỹ năng sống"
  },
  {
   "id": 51788066,
   "title": "MC Quyền Linh khen vợ bản lĩnh, dạy con gái Lọ Lem cách đối mặt áp lực",
   "url": "https://baomoi.com/mc-quyen-linh-khen-vo-ban-linh-day-con-gai-lo-lem-cach-doi-mat-ap-luc-c51788066.epi",
   "source": "Báo VietnamNet",
   "date": "2025-03-24",
   "ts": 1742772900,
   "thumb": "https://photo-baomoi.bmcdn.me/w700_r16x9/2025_03_24_23_51788066/4df72c242d6ac4349d7b.jpg",
   "isVideo": true,
   "category": "Tâm lý & Kỹ năng sống"
  },
  {
   "id": 51729598,
   "title": "Những kiểu ăn sáng phá dạ dày số một",
   "url": "https://baomoi.com/nhung-kieu-an-sang-pha-da-day-so-mot-c51729598.epi",
   "source": "Tạp chí Tri thức",
   "date": "2025-03-17",
   "ts": 1742169690,
   "thumb": "https://photo-baomoi.bmcdn.me/w700_r16x9/2025_03_17_119_51729598/4664675969178049d906.jpg",
   "isVideo": false,
   "category": "Sức khỏe & Dinh dưỡng"
  },
  {
   "id": 51729604,
   "title": "7 dấu hiệu của một người phụ nữ tử tế",
   "url": "https://baomoi.com/7-dau-hieu-cua-mot-nguoi-phu-nu-tu-te-c51729604.epi",
   "source": "Tạp chí Tri thức",
   "date": "2025-03-17",
   "ts": 1742169426,
   "thumb": "https://photo-baomoi.bmcdn.me/w700_r16x9/2025_03_17_119_51729604/e495eea8e0e609b850f7.jpg",
   "isVideo": false,
   "category": "Tâm lý & Kỹ năng sống"
  },
  {
   "id": 51724245,
   "title": "Có lòng giúp người, hãy học cách quên đi",
   "url": "https://baomoi.com/co-long-giup-nguoi-hay-hoc-cach-quen-di-c51724245.epi",
   "source": "Tạp chí Tri thức",
   "date": "2025-03-16",
   "ts": 1742088304,
   "thumb": "https://photo-baomoi.bmcdn.me/w700_r16x9/2025_03_16_119_51724245/1413696964278d79d436.jpg",
   "isVideo": false,
   "category": "Tâm lý & Kỹ năng sống"
  },
  {
   "id": 51680957,
   "title": "6 loại nước tốt cho sức khỏe nên uống vào buổi sáng",
   "url": "https://baomoi.com/6-loai-nuoc-tot-cho-suc-khoe-nen-uong-vao-buoi-sang-c51680957.epi",
   "source": "Báo VTC News",
   "date": "2025-03-11",
   "ts": 1741659960,
   "thumb": "https://photo-baomoi.bmcdn.me/w700_r16x9/2025_03_11_83_51680957/fbf649515f1fb641ef0e.jpg",
   "isVideo": false,
   "category": "Sức khỏe & Dinh dưỡng"
  },
  {
   "id": 51664261,
   "title": "Ukraine, những sự lựa chọn và suy ngẫm về Việt Nam",
   "url": "https://baomoi.com/ukraine-nhung-su-lua-chon-va-suy-ngam-ve-viet-nam-c51664261.epi",
   "source": "Báo Thế Giới & Việt Nam",
   "date": "2025-03-08",
   "ts": 1741447620,
   "thumb": "https://photo-baomoi.bmcdn.me/w700_r16x9/2025_03_08_194_51664261/1a45b764b62a5f74063b.jpg",
   "isVideo": false,
   "category": "Tâm lý & Kỹ năng sống"
  },
  {
   "id": 51632052,
   "title": "Hay bị mất tập trung: Hãy xem chế độ ăn uống có 5 loại thực phẩm này không?",
   "url": "https://baomoi.com/hay-bi-mat-tap-trung-hay-xem-che-do-an-uong-co-5-loai-thuc-pham-nay-khong-c51632052.epi",
   "source": "Báo VietnamPlus",
   "date": "2025-03-05",
   "ts": 1741143240,
   "thumb": "https://photo-baomoi.bmcdn.me/w700_r16x9/2025_03_05_293_51632052/b8f68faa91e478ba21f5.jpg",
   "isVideo": false,
   "category": "Sức khỏe & Dinh dưỡng"
  },
  {
   "id": 51598294,
   "title": "18 số điện thoại lừa đảo đầu 024, tuyệt đối không được nhấc máy",
   "url": "https://baomoi.com/18-so-dien-thoai-lua-dao-dau-024-tuyet-doi-khong-duoc-nhac-may-c51598294.epi",
   "source": "Báo Tri thức & Cuộc sống",
   "date": "2025-02-28",
   "ts": 1740748200,
   "thumb": "https://photo-baomoi.bmcdn.me/w700_r16x9/2025_02_28_180_51598294/d987d06cf2221b7c4233.jpg",
   "isVideo": false,
   "category": "Đời sống & Cảnh giác"
  },
  {
   "id": 51580023,
   "title": "Cha là đại tá, con là hoa hậu: Chuyện chưa kể về gia đình Bảo Ngọc",
   "url": "https://baomoi.com/cha-la-dai-ta-con-la-hoa-hau-chuyen-chua-ke-ve-gia-dinh-bao-ngoc-c51580023.epi",
   "source": "Báo VietnamNet",
   "date": "2025-02-27",
   "ts": 1740612480,
   "thumb": "https://photo-baomoi.bmcdn.me/w700_r16x9/2025_02_27_23_51580023/23622972093ce062b92d.jpg",
   "isVideo": true,
   "category": "Gia đình & Nuôi dạy con"
  },
  {
   "id": 51538791,
   "title": "8 câu nói trẻ không muốn nghe từ cha mẹ",
   "url": "https://baomoi.com/8-cau-noi-tre-khong-muon-nghe-tu-cha-me-c51538791.epi",
   "source": "Tạp chí Tri thức",
   "date": "2025-02-22",
   "ts": 1740182413,
   "thumb": "https://photo-baomoi.bmcdn.me/w700_r16x9/2025_02_22_119_51538791/2c5217d83d96d4c88d87.jpg",
   "isVideo": false,
   "category": "Gia đình & Nuôi dạy con"
  },
  {
   "id": 51538723,
   "title": "3 nguyên tắc giúp mẹ chồng nàng dâu chung sống hòa hợp",
   "url": "https://baomoi.com/3-nguyen-tac-giup-me-chong-nang-dau-chung-song-hoa-hop-c51538723.epi",
   "source": "Báo VietnamNet",
   "date": "2025-02-22",
   "ts": 1740182880,
   "thumb": "https://photo-baomoi.bmcdn.me/w700_r16x9/2025_02_22_23_51538723/4fa7972fbd61543f0d70.jpg",
   "isVideo": false,
   "category": "Gia đình & Nuôi dạy con"
  },
  {
   "id": 51531524,
   "title": "Cảnh giác chiêu trò lừa đảo từ các cuộc gọi không nói gì",
   "url": "https://baomoi.com/canh-giac-chieu-tro-lua-dao-tu-cac-cuoc-goi-khong-noi-gi-c51531524.epi",
   "source": "Báo Sức Khỏe & Đời Sống",
   "date": "2025-02-21",
   "ts": 1740109440,
   "thumb": "https://photo-baomoi.bmcdn.me/w700_r16x9/2025_02_21_94_51531524/92c1755f5c11b54fec00.jpg",
   "isVideo": false,
   "category": "Đời sống & Cảnh giác"
  },
  {
   "id": 51529253,
   "title": "Gia đình bất hòa vì dừng… học thêm",
   "url": "https://baomoi.com/gia-dinh-bat-hoa-vi-dung-hoc-them-c51529253.epi",
   "source": "Tạp chí Gia Đình Việt Nam",
   "date": "2025-02-21",
   "ts": 1740092400,
   "thumb": "https://photo-baomoi.bmcdn.me/w700_r16x9/2025_02_21_251_51529253/c7344e9367dd8e83d7cc.jpg",
   "isVideo": false,
   "category": "Gia đình & Nuôi dạy con"
  },
  {
   "id": 51520007,
   "title": "Hành động của ông Trump gây bất ổn",
   "url": "https://baomoi.com/hanh-dong-cua-ong-trump-gay-bat-on-c51520007.epi",
   "source": "Báo Tiền Phong",
   "date": "2025-02-20",
   "ts": 1740008220,
   "thumb": "https://photo-baomoi.bmcdn.me/w700_r16x9/2025_02_20_20_51520007/3d8b6c4e4400ad5ef411.jpg",
   "isVideo": false,
   "category": "Ngoại giao & Thế giới"
  },
  {
   "id": 51482770,
   "title": "Vinicius khiến Real Madrid khó xử",
   "url": "https://baomoi.com/vinicius-khien-real-madrid-kho-xu-c51482770.epi",
   "source": "Tạp chí Tri thức",
   "date": "2025-02-15",
   "ts": 1739595659,
   "thumb": "https://photo-baomoi.bmcdn.me/w700_r16x9/2025_02_15_119_51482770/a3dc571e64508d0ed441.jpg",
   "isVideo": false,
   "category": "Thể thao"
  }
 ]
}